sensespace_did/__init__.py
sensespace_did/core.py
sensespace_did/fastmcp.py
sensespace_did-0.1.0.dist-info/METADATA
sensespace_did-0.1.0.dist-info/WHEEL
sensespace_did-0.1.0.dist-info/licenses/LICENSE
sensespace_did-0.1.0.dist-info/RECORD
