Metadata-Version: 2.4
Name: sensespace-did
Version: 0.1.0
Summary: SenseSpace DID token verification library
Project-URL: Homepage, https://github.com/verisense-network/sensespace-did
Project-URL: Bug Tracker, https://github.com/verisense-network/sensespace-did/issues
Author-email: Shiotoli <shiotoli@gmail.com>
License-Expression: MIT
License-File: LICENSE
Keywords: did,ed25519,jwt,sensespace,ss58,verification
Classifier: Development Status :: 4 - Beta
Classifier: Intended Audience :: Developers
Classifier: Programming Language :: Python :: 3
Classifier: Programming Language :: Python :: 3.10
Classifier: Programming Language :: Python :: 3.11
Classifier: Programming Language :: Python :: 3.12
Requires-Python: >=3.10
Requires-Dist: base58>=2.1.1
Requires-Dist: cryptography>=41.0.0
Requires-Dist: fastmcp>=2.11.0
Requires-Dist: httpx>=0.25.0
Requires-Dist: pyjwt[crypto]>=2.8.0
Provides-Extra: dev
Requires-Dist: black>=23.0.0; extra == 'dev'
Requires-Dist: pytest>=7.0.0; extra == 'dev'
Requires-Dist: ruff>=0.1.0; extra == 'dev'
